[
    {
      "song_id": "12345",
      "artist": "Example Artist",
      "duration": 240,
      "release_year": 2022
    },
    {
      "song_id": "67890",
      "artist": "Another Artist",
      "duration": 180,
      "release_year": 2021
    },
    {
      "song_id": "54321",
      "artist": "Yet Another Artist",
      "duration": 320,
      "release_year": 2023
    },
    {
      "song_id": "11111",
      "artist": "New Artist",
      "duration": 200,
      "release_year": 2020
    },
    {
      "song_id": "22222",
      "artist": "Different Artist",
      "duration": 280,
      "release_year": 2019
    },
    {
      "song_id": "33333",
      "artist": "Unique Artist",
      "duration": 300,
      "release_year": 2024
    }
  ]
  